tacq/AddRule.py
tacq/CSP.py
tacq/IterativeTemplate.py
tacq/Relation.py
tacq/SolverOrTools.py
tacq/Template.py
tacq/TemplateAcquisition.py
tacq/__init__.py
tacq/abstractSolver.py
tacq-0.0.3.dist-info/METADATA
tacq-0.0.3.dist-info/WHEEL
tacq-0.0.3.dist-info/top_level.txt
tacq-0.0.3.dist-info/RECORD
