Metadata-Version: 2.4
Name: tacq
Version: 0.0.3
Summary: A framework for learning compact representations of constraint networks.
Author-email: Areski Himeur <areski.himeur@lirmm.fr>
Project-URL: Homepage, https://github.com/Hareski/TAcq
Project-URL: Issues, https://github.com/Hareski/TAcq/issues
Classifier: Programming Language :: Python :: 3
Classifier: License :: OSI Approved :: Academic Free License (AFL)
Classifier: Operating System :: OS Independent
Requires-Python: >=3.10
Requires-Dist: ortools>=9.14.6206
Requires-Dist: typing_extensions>=4.14.1
Requires-Dist: languageFreeAcq>=0.0.7
